oled_status/__init__.py
oled_status/draw.py
oled_status/manager.py
oled_status/server.py
oled_status/fonts/OpenSans-Bold.ttf
oled_status/fonts/ProggyVector Regular.ttf
oled_status-0.0.3.dist-info/LICENSE
oled_status-0.0.3.dist-info/METADATA
oled_status-0.0.3.dist-info/WHEEL
oled_status-0.0.3.dist-info/top_level.txt
oled_status-0.0.3.dist-info/RECORD
