Metadata-Version: 2.1
Name: oled-status
Version: 0.0.3
Summary: Status message logger for embedded systems equipped with a small OLED display.
Home-page: https://github.com/FlantasticDan/oled-status
Author: Daniel Flanagan
License: UNKNOWN
Project-URL: Bug Tracker, https://github.com/FlantasticDan/oled-status/issues
Platform: UNKNOWN
Classifier: Programming Language :: Python :: 3
Classifier: License :: OSI Approved :: MIT License
Classifier: Operating System :: OS Independent
Requires-Python: >=3.9
License-File: LICENSE
Requires-Dist: httpx
Provides-Extra: draw
Requires-Dist: Pillow ; extra == 'draw'
Provides-Extra: server
Requires-Dist: adafruit-circuitpython-ssd1306 ; extra == 'server'
Requires-Dist: Pillow ; extra == 'server'
Requires-Dist: flask ; extra == 'server'
Requires-Dist: gevent ; extra == 'server'
